pyanp/__init__.py
pyanp/ahptree.py
pyanp/anp.py
pyanp/direct.py
pyanp/exmats.py
pyanp/general.py
pyanp/limitmatrix.py
pyanp/pairwise.py
pyanp/prioritizer.py
pyanp/priority.py
pyanp/rating.py
pyanp/rowsens.py
pyanp-0.3.1.dist-info/METADATA
pyanp-0.3.1.dist-info/RECORD
pyanp-0.3.1.dist-info/WHEEL
pyanp-0.3.1.dist-info/top_level.txt
