Metadata-Version: 2.1
Name: pyanp
Version: 0.3.1
Summary: Math library for ANP/AHP calculations
Home-page: https://github.com/wjladams/pyanp
Author: Bill Adams
Author-email: wjadams@decisionlens.com
License: MIT
Platform: UNKNOWN
Requires-Python: >=3.6
Requires-Dist: numpy
Requires-Dist: pandas
